pydirdbjson/__init__.py
pydirdbjson/main.py
pydirdbjson-1.0.0.dist-info/licenses/LICENSE
pydirdbjson-1.0.0.dist-info/METADATA
pydirdbjson-1.0.0.dist-info/WHEEL
pydirdbjson-1.0.0.dist-info/top_level.txt
pydirdbjson-1.0.0.dist-info/RECORD
