Metadata-Version: 2.4
Name: pydirdbjson
Version: 1.0.0
Summary: A Database in JSON on directory
Author-email: Ricardo P Ferreras <ricardo.ferreras@gmail.com>
License-Expression: MIT
Project-URL: Homepage, https://github.com/FerrerasRP/Projeto-PyDirDbJson
Project-URL: Issues, https://github.com/FerrerasRP/Projeto-PyDirDbJson/issues
Project-URL: Changelog, https://github.com/FerrerasRP/Projeto-PyDirDbJson/blob/main/CHANGELOG.md
Keywords: json,database,file
Classifier: Programming Language :: Python :: 3
Classifier: Operating System :: OS Independent
Requires-Python: >=3.9
License-File: LICENSE
Dynamic: license-file
